seremi/EMIFile.py
seremi/SERFile.py
seremi/__init__.py
seremi-0.0.2.dist-info/METADATA
seremi-0.0.2.dist-info/WHEEL
seremi-0.0.2.dist-info/licenses/LICENSE
seremi-0.0.2.dist-info/RECORD
