Metadata-Version: 2.4
Name: seremi
Version: 0.0.2
Summary: Read SER & EMI microscope images and metadata.
Project-URL: Homepage, https://github.com/theNelsonLab/seremi
Project-URL: Issues, https://github.com/theNelsonLab/seremi/issues
Author-email: Sam Foxman <sfoxman@caltech.edu>
License-Expression: GPL-3.0-or-later
License-File: LICENSE
Classifier: Operating System :: OS Independent
Classifier: Programming Language :: Python :: 3
Requires-Python: >=3.8
Requires-Dist: numpy>=2
Provides-Extra: docs
Requires-Dist: sphinx==8.1.3; extra == 'docs'
